circlemap/Coverage.py
circlemap/__init__.py
circlemap/__version__.py
circlemap/bam2bam.py
circlemap/call.py
circlemap/circle_map.py
circlemap/extract_circle_SV_reads.py
circlemap/realigner.py
circlemap/repeats.py
circlemap/simulations.py
circlemap/utils.py
Circle_Map-1.1.4.dist-info/LICENSE
Circle_Map-1.1.4.dist-info/METADATA
Circle_Map-1.1.4.dist-info/WHEEL
Circle_Map-1.1.4.dist-info/entry_points.txt
Circle_Map-1.1.4.dist-info/top_level.txt
Circle_Map-1.1.4.dist-info/RECORD
