Metadata-Version: 2.1
Name: Circle-Map
Version: 1.1.4
Summary: Circular DNA analysis tools
Home-page: https://github.com/iprada/Circle-Map
Author: Inigo Prada-Luengo
Author-email: UNKNOWN
License: UNKNOWN
Platform: UNKNOWN
Classifier: License :: OSI Approved :: MIT License
Requires-Dist: pysam (>=0.15.2)
Requires-Dist: pybedtools (>=0.8.0)
Requires-Dist: pandas (>=0.24.2)
Requires-Dist: biopython (>=1.73)
Requires-Dist: numpy (>=1.16.3)
Requires-Dist: edlib (>=1.2.3)
Requires-Dist: numba (>=0.45.0)
Requires-Dist: tqdm (>=4.31.1)
Requires-Dist: scipy (>=1.2.1)
